.coveragerc
.gitignore
.travis.yml
LICENSE
MANIFEST.in
README.rst
setup.py
tox.ini
docs/HISTORY.txt
docs/INSTALL.txt
docs/LICENSE.GPL
docs/LICENSE.txt
fidetournament/__init__.py
fidetournament/player.py
fidetournament/tournament.py
fidetournament.egg-info/PKG-INFO
fidetournament.egg-info/SOURCES.txt
fidetournament.egg-info/dependency_links.txt
fidetournament.egg-info/entry_points.txt
fidetournament.egg-info/not-zip-safe
fidetournament.egg-info/requires.txt
fidetournament.egg-info/top_level.txt
tests/__init__.py
tests/test_demo.trf
tests/tests.py