Metadata-Version: 1.0
Name: fidetournament
Version: 0.3
Summary: FIDE Tournament Report File (Krause format) parser and creator
Home-page: https://github.com/erral/fidetournament
Author: Mikel Larreategi
Author-email: larreategi@eibar.org
License: GPL
Keywords: chess fide parser
Platform: UNKNOWN
